CHANGES.txt
MANIFEST.in
README.md
requirements-dev.txt
requirements.txt
setup.py
GeobricksProcessing.egg-info/PKG-INFO
GeobricksProcessing.egg-info/SOURCES.txt
GeobricksProcessing.egg-info/dependency_links.txt
GeobricksProcessing.egg-info/pbr.json
GeobricksProcessing.egg-info/top_level.txt
geobricks_processing/__init__.py
geobricks_processing/__init__.pyc
geobricks_processing/config/__init__.py
geobricks_processing/config/config.py
geobricks_processing/core/__init__.py
geobricks_processing/core/__init__.pyc
geobricks_processing/core/processing_core.py
geobricks_processing/core/processing_core.pyc
geobricks_processing/rest/__init__.py
geobricks_processing/rest/processing_main.py
geobricks_processing/rest/processing_rest.py