Metadata-Version: 1.0
Name: GeobricksProcessing
Version: 0.0.5
Summary: Geobricks processing library for raster data.
Home-page: http://pypi.python.org/pypi/GeobricksProcessing/
Author: Simone Murzilli; Guido Barbaglia
Author-email: geobrickspy@gmail.com
License: LICENSE.txt
Keywords: geobricks,processing,raster,gis,gdal
Platform: UNKNOWN
